MANIFEST.in
README.rst
easytextract_pyinstaller.spec
setup.py
easytextract/__main__.py
easytextract/_version.py
easytextract/easytextract.py
easytextract.egg-info/PKG-INFO
easytextract.egg-info/SOURCES.txt
easytextract.egg-info/dependency_links.txt
easytextract.egg-info/entry_points.txt
easytextract.egg-info/top_level.txt
easytextract/csg_fileutil_libs/__init__.py
easytextract/csg_fileutil_libs/argparse.py
easytextract/csg_fileutil_libs/aux_funcs.py
easytextract/csg_fileutil_libs/tee.py
easytextract/csg_fileutil_libs/gooey/LICENSE.txt
easytextract/csg_fileutil_libs/gooey/README.md
easytextract/csg_fileutil_libs/gooey/TODO.txt
easytextract/csg_fileutil_libs/gooey/__init__.py
easytextract/csg_fileutil_libs/gooey/__main__.py
easytextract/csg_fileutil_libs/gooey/dev_utils/__init__.py
easytextract/csg_fileutil_libs/gooey/dev_utils/ast_inspector.py
easytextract/csg_fileutil_libs/gooey/gui/__init__.py
easytextract/csg_fileutil_libs/gooey/gui/action_sorter.py
easytextract/csg_fileutil_libs/gooey/gui/application.py
easytextract/csg_fileutil_libs/gooey/gui/argparse_test_data.py
easytextract/csg_fileutil_libs/gooey/gui/build_spec_validator.py
easytextract/csg_fileutil_libs/gooey/gui/chooser_runner.py
easytextract/csg_fileutil_libs/gooey/gui/client_app.py
easytextract/csg_fileutil_libs/gooey/gui/component_builder.py
easytextract/csg_fileutil_libs/gooey/gui/component_factory.py
easytextract/csg_fileutil_libs/gooey/gui/component_register.py
easytextract/csg_fileutil_libs/gooey/gui/components.py
easytextract/csg_fileutil_libs/gooey/gui/controller.py
easytextract/csg_fileutil_libs/gooey/gui/display_main.py
easytextract/csg_fileutil_libs/gooey/gui/events.py
easytextract/csg_fileutil_libs/gooey/gui/gooey_config.json
easytextract/csg_fileutil_libs/gooey/gui/image_repository.py
easytextract/csg_fileutil_libs/gooey/gui/imageutil.py
easytextract/csg_fileutil_libs/gooey/gui/message_event.py
easytextract/csg_fileutil_libs/gooey/gui/message_router.py
easytextract/csg_fileutil_libs/gooey/gui/msg_dialog.py
easytextract/csg_fileutil_libs/gooey/gui/option_reader.py
easytextract/csg_fileutil_libs/gooey/gui/pubsub.py
easytextract/csg_fileutil_libs/gooey/gui/settings.py
