Metadata-Version: 1.1
Name: easytextract
Version: 1.1.5
Summary: Easy to use text extractor, from PDF, DOC, DOCX and other document types, using the awesome Textract, including if necessary using OCR (via Tesseract).
Home-page: https://github.com/LRQ3000/easytextract
Author: Stephen Larroque
Author-email: lrq3000@gmail.com
License: MIT Licence
Keywords: text extractor pdf doc docx word utility ocr
Platform: any
Classifier: Development Status :: 4 - Beta
Classifier: License :: OSI Approved :: MIT License
Classifier: Environment :: Console
Classifier: Environment :: Win32 (MS Windows)
Classifier: Environment :: MacOS X
Classifier: Environment :: X11 Applications
Classifier: Operating System :: Microsoft :: Windows
Classifier: Operating System :: MacOS :: MacOS X
Classifier: Operating System :: POSIX
Classifier: Operating System :: POSIX :: Linux
Classifier: Operating System :: POSIX :: BSD
Classifier: Operating System :: POSIX :: BSD :: FreeBSD
Classifier: Operating System :: POSIX :: SunOS/Solaris
Classifier: Programming Language :: Python
Classifier: Programming Language :: Python :: 2
Classifier: Programming Language :: Python :: 2.7
Classifier: Programming Language :: Python :: Implementation :: PyPy
Classifier: Topic :: Software Development :: Libraries
Classifier: Topic :: Utilities
Classifier: Intended Audience :: End Users/Desktop
